filmhub_api/__init__.py
filmhub_api/session.py
filmhub_api/session_py2.py
filmhub_python_api-1.1.4.post2.dist-info/METADATA
filmhub_python_api-1.1.4.post2.dist-info/WHEEL
filmhub_python_api-1.1.4.post2.dist-info/top_level.txt
filmhub_python_api-1.1.4.post2.dist-info/RECORD
