Metadata-Version: 2.1
Name: filmhub-python-api
Version: 1.1.4.post2
Summary: A Python API for controlling FilmHUB fast film delivery software
Home-page: https://github.com/henriknorin/filmhub-python-api.git
Author: Henrik Norin
Author-email: henrik.norin@filmhubsoftware.com
License: UNKNOWN
Platform: UNKNOWN
Classifier: Programming Language :: Python :: 2
Classifier: License :: OSI Approved :: MIT License
Classifier: Operating System :: OS Independent
